{
  "hints": [],
  "groups": [
    {
      "sourceType": "net.guides.springboot.springbootmultipledatasources.config.OrdersDataSourceConfig",
      "name": "datasource.orders",
      "sourceMethod": "public org.springframework.boot.autoconfigure.jdbc.DataSourceProperties ordersDataSourceProperties() ",
      "type": "org.springframework.boot.autoconfigure.jdbc.DataSourceProperties"
    },
    {
      "sourceType": "org.springframework.boot.autoconfigure.jdbc.DataSourceProperties",
      "name": "datasource.orders.xa",
      "sourceMethod": "public org.springframework.boot.autoconfigure.jdbc.DataSourceProperties.Xa getXa() ",
      "type": "org.springframework.boot.autoconfigure.jdbc.DataSourceProperties$Xa"
    },
    {
      "sourceType": "net.guides.springboot.springbootmultipledatasources.config.SecurityDataSourceConfig",
      "name": "datasource.security",
      "sourceMethod": "public org.springframework.boot.autoconfigure.jdbc.DataSourceProperties securityDataSourceProperties() ",
      "type": "org.springframework.boot.autoconfigure.jdbc.DataSourceProperties"
    },
    {
      "sourceType": "org.springframework.boot.autoconfigure.jdbc.DataSourceProperties",
      "name": "datasource.security.xa",
      "sourceMethod": "public org.springframework.boot.autoconfigure.jdbc.DataSourceProperties.Xa getXa() ",
      "type": "org.springframework.boot.autoconfigure.jdbc.DataSourceProperties$Xa"
    }
  ],
  "properties": [
    {
      "sourceType": "org.springframework.boot.autoconfigure.jdbc.DataSourceProperties",
      "name": "datasource.orders.continue-on-error",
      "type": "java.lang.Boolean"
    },
    {
      "sourceType": "org.springframework.boot.autoconfigure.jdbc.DataSourceProperties",
      "name": "datasource.orders.data",
      "type": "java.util.List<java.lang.String>"
    },
    {
      "sourceType": "org.springframework.boot.autoconfigure.jdbc.DataSourceProperties",
      "name": "datasource.orders.data-password",
      "type": "java.lang.String"
    },
    {
      "sourceType": "org.springframework.boot.autoconfigure.jdbc.DataSourceProperties",
      "name": "datasource.orders.data-username",
      "type": "java.lang.String"
    },
    {
      "sourceType": "org.springframework.boot.autoconfigure.jdbc.DataSourceProperties",
      "name": "datasource.orders.driver-class-name",
      "type": "java.lang.String"
    },
    {
      "sourceType": "org.springframework.boot.autoconfigure.jdbc.DataSourceProperties",
      "name": "datasource.orders.generate-unique-name",
      "type": "java.lang.Boolean"
    },
    {
      "sourceType": "org.springframework.boot.autoconfigure.jdbc.DataSourceProperties",
      "name": "datasource.orders.initialization-mode",
      "type": "org.springframework.boot.jdbc.DataSourceInitializationMode"
    },
    {
      "sourceType": "org.springframework.boot.autoconfigure.jdbc.DataSourceProperties",
      "name": "datasource.orders.jndi-name",
      "type": "java.lang.String"
    },
    {
      "sourceType": "org.springframework.boot.autoconfigure.jdbc.DataSourceProperties",
      "name": "datasource.orders.name",
      "type": "java.lang.String"
    },
    {
      "sourceType": "org.springframework.boot.autoconfigure.jdbc.DataSourceProperties",
      "name": "datasource.orders.password",
      "type": "java.lang.String"
    },
    {
      "sourceType": "org.springframework.boot.autoconfigure.jdbc.DataSourceProperties",
      "name": "datasource.orders.platform",
      "type": "java.lang.String"
    },
    {
      "sourceType": "org.springframework.boot.autoconfigure.jdbc.DataSourceProperties",
      "name": "datasource.orders.schema",
      "type": "java.util.List<java.lang.String>"
    },
    {
      "sourceType": "org.springframework.boot.autoconfigure.jdbc.DataSourceProperties",
      "name": "datasource.orders.schema-password",
      "type": "java.lang.String"
    },
    {
      "sourceType": "org.springframework.boot.autoconfigure.jdbc.DataSourceProperties",
      "name": "datasource.orders.schema-username",
      "type": "java.lang.String"
    },
    {
      "sourceType": "org.springframework.boot.autoconfigure.jdbc.DataSourceProperties",
      "name": "datasource.orders.separator",
      "type": "java.lang.String"
    },
    {
      "sourceType": "org.springframework.boot.autoconfigure.jdbc.DataSourceProperties",
      "name": "datasource.orders.sql-script-encoding",
      "type": "java.nio.charset.Charset"
    },
    {
      "sourceType": "org.springframework.boot.autoconfigure.jdbc.DataSourceProperties",
      "name": "datasource.orders.type",
      "type": "java.lang.Class<? extends javax.sql.DataSource>"
    },
    {
      "sourceType": "org.springframework.boot.autoconfigure.jdbc.DataSourceProperties",
      "name": "datasource.orders.url",
      "type": "java.lang.String"
    },
    {
      "sourceType": "org.springframework.boot.autoconfigure.jdbc.DataSourceProperties",
      "name": "datasource.orders.username",
      "type": "java.lang.String"
    },
    {
      "sourceType": "org.springframework.boot.autoconfigure.jdbc.DataSourceProperties$Xa",
      "name": "datasource.orders.xa.data-source-class-name",
      "type": "java.lang.String"
    },
    {
      "sourceType": "org.springframework.boot.autoconfigure.jdbc.DataSourceProperties$Xa",
      "name": "datasource.orders.xa.properties",
      "type": "java.util.Map<java.lang.String,java.lang.String>"
    },
    {
      "sourceType": "org.springframework.boot.autoconfigure.jdbc.DataSourceProperties",
      "name": "datasource.security.continue-on-error",
      "type": "java.lang.Boolean"
    },
    {
      "sourceType": "org.springframework.boot.autoconfigure.jdbc.DataSourceProperties",
      "name": "datasource.security.data",
      "type": "java.util.List<java.lang.String>"
    },
    {
      "sourceType": "org.springframework.boot.autoconfigure.jdbc.DataSourceProperties",
      "name": "datasource.security.data-password",
      "type": "java.lang.String"
    },
    {
      "sourceType": "org.springframework.boot.autoconfigure.jdbc.DataSourceProperties",
      "name": "datasource.security.data-username",
      "type": "java.lang.String"
    },
    {
      "sourceType": "org.springframework.boot.autoconfigure.jdbc.DataSourceProperties",
      "name": "datasource.security.driver-class-name",
      "type": "java.lang.String"
    },
    {
      "sourceType": "org.springframework.boot.autoconfigure.jdbc.DataSourceProperties",
      "name": "datasource.security.generate-unique-name",
      "type": "java.lang.Boolean"
    },
    {
      "sourceType": "org.springframework.boot.autoconfigure.jdbc.DataSourceProperties",
      "name": "datasource.security.initialization-mode",
      "type": "org.springframework.boot.jdbc.DataSourceInitializationMode"
    },
    {
      "sourceType": "org.springframework.boot.autoconfigure.jdbc.DataSourceProperties",
      "name": "datasource.security.jndi-name",
      "type": "java.lang.String"
    },
    {
      "sourceType": "org.springframework.boot.autoconfigure.jdbc.DataSourceProperties",
      "name": "datasource.security.name",
      "type": "java.lang.String"
    },
    {
      "sourceType": "org.springframework.boot.autoconfigure.jdbc.DataSourceProperties",
      "name": "datasource.security.password",
      "type": "java.lang.String"
    },
    {
      "sourceType": "org.springframework.boot.autoconfigure.jdbc.DataSourceProperties",
      "name": "datasource.security.platform",
      "type": "java.lang.String"
    },
    {
      "sourceType": "org.springframework.boot.autoconfigure.jdbc.DataSourceProperties",
      "name": "datasource.security.schema",
      "type": "java.util.List<java.lang.String>"
    },
    {
      "sourceType": "org.springframework.boot.autoconfigure.jdbc.DataSourceProperties",
      "name": "datasource.security.schema-password",
      "type": "java.lang.String"
    },
    {
      "sourceType": "org.springframework.boot.autoconfigure.jdbc.DataSourceProperties",
      "name": "datasource.security.schema-username",
      "type": "java.lang.String"
    },
    {
      "sourceType": "org.springframework.boot.autoconfigure.jdbc.DataSourceProperties",
      "name": "datasource.security.separator",
      "type": "java.lang.String"
    },
    {
      "sourceType": "org.springframework.boot.autoconfigure.jdbc.DataSourceProperties",
      "name": "datasource.security.sql-script-encoding",
      "type": "java.nio.charset.Charset"
    },
    {
      "sourceType": "org.springframework.boot.autoconfigure.jdbc.DataSourceProperties",
      "name": "datasource.security.type",
      "type": "java.lang.Class<? extends javax.sql.DataSource>"
    },
    {
      "sourceType": "org.springframework.boot.autoconfigure.jdbc.DataSourceProperties",
      "name": "datasource.security.url",
      "type": "java.lang.String"
    },
    {
      "sourceType": "org.springframework.boot.autoconfigure.jdbc.DataSourceProperties",
      "name": "datasource.security.username",
      "type": "java.lang.String"
    },
    {
      "sourceType": "org.springframework.boot.autoconfigure.jdbc.DataSourceProperties$Xa",
      "name": "datasource.security.xa.data-source-class-name",
      "type": "java.lang.String"
    },
    {
      "sourceType": "org.springframework.boot.autoconfigure.jdbc.DataSourceProperties$Xa",
      "name": "datasource.security.xa.properties",
      "type": "java.util.Map<java.lang.String,java.lang.String>"
    }
  ]
}